sonarqube/__init__.py
sonarqube/rest/__init__.py
sonarqube/rest/audit_logs.py
sonarqube/rest/auth.py
sonarqube/rest/ce.py
sonarqube/rest/duplications.py
sonarqube/rest/editions.py
sonarqube/rest/favorites.py
sonarqube/rest/issues.py
sonarqube/rest/languages.py
sonarqube/rest/measures.py
sonarqube/rest/metrics.py
sonarqube/rest/project_analyses.py
sonarqube/rest/project_badges.py
sonarqube/rest/project_branches.py
sonarqube/rest/project_dump.py
sonarqube/rest/project_links.py
sonarqube/rest/project_tags.py
sonarqube/rest/projects.py
sonarqube/rest/qualitygates.py
sonarqube/rest/qualityprofiles.py
sonarqube/rest/rules.py
sonarqube/rest/server.py
sonarqube/rest/user_groups.py
sonarqube/rest/user_tokens.py
sonarqube/rest/users.py
sonarqube/rest/views.py
sonarqube/utils/__init__.py
sonarqube/utils/common.py
sonarqube/utils/config.py
sonarqube/utils/exceptions.py
sonarqube/utils/rest_client.py
python_sonarqube_api-2.0.5.dist-info/LICENSE
python_sonarqube_api-2.0.5.dist-info/METADATA
python_sonarqube_api-2.0.5.dist-info/WHEEL
python_sonarqube_api-2.0.5.dist-info/top_level.txt
python_sonarqube_api-2.0.5.dist-info/RECORD
