Metadata-Version: 2.1
Name: python-sonarqube-api
Version: 2.0.5
Summary: Python wrapper for the SonarQube and SonarCloud API.
Home-page: https://github.com/shijl0925/python-sonarqube-api
Author: Jialiang Shi
Author-email: kevin09254930sjl@gmail.com
License: AGPLv3
Keywords: api sonarqube sonar client wrapper sonarcloud
Classifier: Development Status :: 5 - Production/Stable
Classifier: Environment :: Plugins
Classifier: Intended Audience :: Developers
Classifier: License :: OSI Approved :: GNU Affero General Public License v3
Classifier: Operating System :: OS Independent
Classifier: Programming Language :: Python :: 2.7
Classifier: Programming Language :: Python :: 3.3
Classifier: Programming Language :: Python :: 3.4
Classifier: Programming Language :: Python :: 3.5
Classifier: Programming Language :: Python :: 3.6
Classifier: Programming Language :: Python :: 3.7
Classifier: Programming Language :: Python :: 3.8
Classifier: Programming Language :: Python :: 3.9
Classifier: Programming Language :: Python :: 3.10
Classifier: Programming Language :: Python :: 3.11
Classifier: Programming Language :: Python :: 3.12
Classifier: Topic :: Software Development
License-File: LICENSE
Requires-Dist: requests
